{"data":{"site":{"siteMetadata":{"title":"TIL"}},"markdownRemark":{"id":"8b024c22-b99c-518e-9ff7-c7687dec6a9c","excerpt":"","htmlAst":{"type":"root","children":[],"data":{"quirksMode":false}},"fields":{"slug":"/ordered-keys-in-js/"},"frontmatter":{"title":"","date":null}}},"pageContext":{"node_id":"8b024c22-b99c-518e-9ff7-c7687dec6a9c","nodeType":"post","title":"Ordered keys in JS objects","slug":"/ordered-keys-in-js/","previous":{"id":"b0266a1b-61a4-5108-b1c6-11e41bef4ae2","fields":{"slug":"/my-immutable-toolkit/"},"frontmatter":{"title":"Tools for immutable work"}},"next":{"id":"4b384b78-b0d0-5fb2-b7f7-64db0af7aaf8","fields":{"slug":"/npm-in-rails/"},"frontmatter":{"title":"Using npm packages in Rails"}}}}