{"data":{"site":{"siteMetadata":{"title":"TIL"}},"markdownRemark":{"id":"256e0edd-ebe4-5545-b9a7-2d53d5707cc4","excerpt":"","htmlAst":{"type":"root","children":[],"data":{"quirksMode":false}},"fields":{"slug":"/extend-sucks/"},"frontmatter":{"title":"","date":null,"description":null,"attachments":null}}},"pageContext":{"node_id":"256e0edd-ebe4-5545-b9a7-2d53d5707cc4","nodeType":"post","title":"@extend sucks","slug":"/extend-sucks/","previous":{"id":"66438fa6-8870-574a-9d53-e6048b1d0083","fields":{"slug":"/es6-class-pitfalls/"},"frontmatter":{"title":"ES6 class pitfalls"}},"next":{"id":"44fb9824-1bd6-5a06-b7c5-90abf1d81320","fields":{"slug":"/get-started-with-ansible/"},"frontmatter":{"title":"Get started with Ansible in 2 minutes"}}}}